typhoon_ocr/__init__.py
typhoon_ocr/ocr_utils.py
typhoon_ocr/pdf_utils.py
typhoon_ocr-0.4.0.dist-info/licenses/LICENSE
typhoon_ocr-0.4.0.dist-info/METADATA
typhoon_ocr-0.4.0.dist-info/WHEEL
typhoon_ocr-0.4.0.dist-info/top_level.txt
typhoon_ocr-0.4.0.dist-info/RECORD
