Metadata-Version: 2.4
Name: typhoon-ocr
Version: 0.4.0
Summary: A package for extracting structured content from PDFs and images using Typhoon OCR models
Author-email: Typhoon OCR Contributors <contact@opentyphoon.ai>
License: Apache-2.0
Project-URL: Homepage, https://github.com/scb-10x/typhoon-ocr
Classifier: Programming Language :: Python :: 3
Classifier: Operating System :: OS Independent
Requires-Python: >=3.7
License-File: LICENSE
Requires-Dist: ftfy
Requires-Dist: pypdf
Requires-Dist: pillow
Requires-Dist: openai
Provides-Extra: dev
Requires-Dist: pytest; extra == "dev"
Requires-Dist: black; extra == "dev"
Requires-Dist: flake8; extra == "dev"
Provides-Extra: app
Requires-Dist: gradio; extra == "app"
Requires-Dist: python-dotenv; extra == "app"
Dynamic: license-file
